stockstats.py
stockstats-0.6.7.dist-info/licenses/LICENSE.txt
stockstats-0.6.7.dist-info/METADATA
stockstats-0.6.7.dist-info/WHEEL
stockstats-0.6.7.dist-info/top_level.txt
stockstats-0.6.7.dist-info/RECORD
