Metadata-Version: 2.4
Name: stockstats
Version: 0.6.7
Summary: DataFrame with inline stock statistics support.
Home-page: https://github.com/jealous/stockstats
Author: Cedric Zhuang
Author-email: jealous@163.com
License: BSD
Keywords: stock statistics indicator
Platform: any
Classifier: Programming Language :: Python
Classifier: Programming Language :: Python :: 3.9
Classifier: Programming Language :: Python :: 3.10
Classifier: Programming Language :: Python :: 3.11
Classifier: Programming Language :: Python :: Implementation :: CPython
Classifier: Natural Language :: English
Classifier: Intended Audience :: Developers
Classifier: Intended Audience :: Financial and Insurance Industry
Classifier: Operating System :: OS Independent
Classifier: Development Status :: 4 - Beta
Classifier: Topic :: Utilities
Classifier: License :: OSI Approved :: BSD License
License-File: LICENSE.txt
Requires-Dist: numpy>=1.16.6
Requires-Dist: pandas>=0.24.2
Dynamic: author
Dynamic: author-email
Dynamic: classifier
Dynamic: description
Dynamic: description-content-type
Dynamic: home-page
Dynamic: keywords
Dynamic: license
Dynamic: license-file
Dynamic: platform
Dynamic: requires-dist
Dynamic: summary
